{
  "gameSlug": "super-integers",
  "gameName": "Super Integer",
  "scenes": [
    {
      "id": "demo1",
      "title": "Scene 1",
      "name": "Integers Base Camp",
      "icon": "🧙‍♂️",
      "enemy": "👾",
      "topic": "Integers",
      "music": "Integers",
      "teach": [
        "This is a demo scene for Integers.",
        "Full question bank can be expanded later."
      ],
      "worked": [
        [
          "Demo",
          "Choose correct."
        ]
      ]
    },
    {
      "id": "demo2",
      "title": "Scene 2",
      "name": "Integers Practice",
      "icon": "🧙‍♂️",
      "enemy": "👾",
      "topic": "Integers",
      "music": "Integers",
      "teach": [
        "Practice Integers.",
        "Add more scenes by editing JSON."
      ],
      "worked": [
        [
          "Demo",
          "Answer = correct."
        ]
      ]
    }
  ]
}